lambda_requests/__init__.py
lambda_requests/lambda_request.py
lambda_requests-1.5.dist-info/AUTHORS.rst
lambda_requests-1.5.dist-info/LICENSE
lambda_requests-1.5.dist-info/METADATA
lambda_requests-1.5.dist-info/WHEEL
lambda_requests-1.5.dist-info/top_level.txt
lambda_requests-1.5.dist-info/RECORD
