Metadata-Version: 2.1
Name: lambda-requests
Version: 1.5
Summary: Use Requests to invoke AWS Lambdas
Home-page: https://github.com/IlyaSukhanov/lambda-requests
Author: Ilya Sukhanov
Author-email: ilya@sukhanov.net
License: MIT license
Keywords: lambda_requests
Platform: UNKNOWN
Classifier: Intended Audience :: Developers
Classifier: License :: OSI Approved :: MIT License
Classifier: Natural Language :: English
Classifier: Programming Language :: Python :: 3
Classifier: Programming Language :: Python :: 3.9
License-File: LICENSE
License-File: AUTHORS.rst
Requires-Dist: boto3
Requires-Dist: lambda-invoke
Requires-Dist: requests
Provides-Extra: testing
Requires-Dist: pip ; extra == 'testing'
Requires-Dist: flake8 ; extra == 'testing'
Requires-Dist: tox ; extra == 'testing'
Requires-Dist: coverage ; extra == 'testing'
Requires-Dist: pytest ; extra == 'testing'
Requires-Dist: pyflakes ; extra == 'testing'
Requires-Dist: pytest-cov ; extra == 'testing'
Requires-Dist: bandit ; extra == 'testing'
Requires-Dist: black ; extra == 'testing'
Requires-Dist: isort ; extra == 'testing'
Requires-Dist: wheel ; extra == 'testing'
Requires-Dist: twine ; extra == 'testing'
Requires-Dist: build ; extra == 'testing'
